pycofitness/__init__.py
pycofitness/main.py
pycofitness/fasta_reader/__init__.py
pycofitness/fasta_reader/fasta_reader.py
pycofitness/logging_config/__init__.py
pycofitness/logging_config/logging_config.py
pycofitness/msa_trimmer/__init__.py
pycofitness/msa_trimmer/msa_trimmer.py
pycofitness/mutation/__init__.py
pycofitness/mutation/mutation.py
pycofitness/plmdca/__init__.py
pycofitness/plmdca/_plmdcaBackend.cpython-39-darwin.so
pycofitness/plmdca/plmdca.py
pycofitness/resmapping/__init__.py
pycofitness/resmapping/resmapping.py
pycofitness-1.4.dist-info/LICENSE.txt
pycofitness-1.4.dist-info/METADATA
pycofitness-1.4.dist-info/WHEEL
pycofitness-1.4.dist-info/entry_points.txt
pycofitness-1.4.dist-info/top_level.txt
pycofitness-1.4.dist-info/RECORD
