Metadata-Version: 2.2
Name: pycofitness
Version: 1.4
Summary: <i>In silico</i> mutagenesis of protein and RNA sequences using coevolution
Home-page: https://github.com/KIT-MBS/pycofitness
Download-URL: https://pypi.org/project/pycofitness/
Author: Fabrizio Pucci, Mehari B. Zerihun
Author-email: Fabrizio.Pucci@ulb.be, mbzerihun@gmail.com
Classifier: Programming Language :: Python :: 3
Classifier: Programming Language :: C++
Classifier: Programming Language :: C
Classifier: License :: OSI Approved :: MIT License
Classifier: Development Status :: 4 - Beta
Classifier: Operating System :: POSIX :: Linux
Classifier: Topic :: Scientific/Engineering :: Bio-Informatics
Requires-Python: >=3.6
License-File: LICENSE.txt
Requires-Dist: llvmlite>0.30.0
Requires-Dist: numpy
Requires-Dist: biopython>=1.74
Dynamic: author
Dynamic: author-email
Dynamic: classifier
Dynamic: description
Dynamic: description-content-type
Dynamic: download-url
Dynamic: home-page
Dynamic: requires-dist
Dynamic: requires-python
Dynamic: summary
